gauntlet_testing_ti/__init__.py
gauntlet_testing_ti/api_client.py
gauntlet_testing_ti/api_response.py
gauntlet_testing_ti/configuration.py
gauntlet_testing_ti/exceptions.py
gauntlet_testing_ti/py.typed
gauntlet_testing_ti/rest.py
gauntlet_testing_ti/api/__init__.py
gauntlet_testing_ti/api/default_api.py
gauntlet_testing_ti/models/__init__.py
gauntlet_testing_ti/models/get_all_weekly_activities200_response.py
gauntlet_testing_ti-0.0.1.dist-info/METADATA
gauntlet_testing_ti-0.0.1.dist-info/WHEEL
gauntlet_testing_ti-0.0.1.dist-info/top_level.txt
gauntlet_testing_ti-0.0.1.dist-info/RECORD
